LICENSE
MANIFEST.in
README.rst
setup.cfg
setup.py
django_enumchoicefield_fork.egg-info/PKG-INFO
django_enumchoicefield_fork.egg-info/SOURCES.txt
django_enumchoicefield_fork.egg-info/dependency_links.txt
django_enumchoicefield_fork.egg-info/not-zip-safe
django_enumchoicefield_fork.egg-info/requires.txt
django_enumchoicefield_fork.egg-info/top_level.txt
enumchoicefield/__init__.py
enumchoicefield/admin.py
enumchoicefield/enum.py
enumchoicefield/fields.py
enumchoicefield/forms.py
enumchoicefield/utils.py
enumchoicefield/version.py
enumchoicefield/tests/__init__.py
enumchoicefield/tests/models.py
enumchoicefield/tests/settings.py
enumchoicefield/tests/test_enum.py
enumchoicefield/tests/test_field.py
enumchoicefield/tests/test_forms.py
enumchoicefield/tests/test_utils.py
enumchoicefield/tests/migrations/0001_initial.py
enumchoicefield/tests/migrations/0002_make_nullable.py
enumchoicefield/tests/migrations/__init__.py