Metadata-Version: 2.1
Name: django-enumchoicefield-fork
Version: 2.1.1
Summary: A choice field for Django using native Python Enums
Home-page: https://github.com/eivindkopperud/django-enumchoicefield-fork
Author: Tim Heap
Author-email: tim@timheap.me
License: BSD License
Platform: UNKNOWN
Classifier: Environment :: Web Environment
Classifier: Intended Audience :: Developers
Classifier: Operating System :: OS Independent
Classifier: Programming Language :: Python
Classifier: Programming Language :: Python :: 3.7
Classifier: Programming Language :: Python :: 3.8
Classifier: Programming Language :: Python :: 3.9
Classifier: Programming Language :: Python :: 3.10
Classifier: Framework :: Django
Classifier: License :: OSI Approved :: BSD License
License-File: LICENSE
